team1ArithmeticTrainer/__init__.py
team1ArithmeticTrainer/__main__.py
team1ArithmeticTrainer/functions.py
arithmeticTrainer-0.0.1.dist-info/LICENSE
arithmeticTrainer-0.0.1.dist-info/METADATA
arithmeticTrainer-0.0.1.dist-info/WHEEL
arithmeticTrainer-0.0.1.dist-info/entry_points.txt
arithmeticTrainer-0.0.1.dist-info/top_level.txt
arithmeticTrainer-0.0.1.dist-info/RECORD
