Metadata-Version: 2.1
Name: arithmeticTrainer
Version: 0.0.1
Summary: A package meant to train mental math and basic arithmetic
Author-email: Kevin Gong <kxg202@nyu.edu>, Dixit Timilsina <dt1930@nyu.edu>, James Liu <sl7059@nyu.edu>
License: GNU GENERAL PUBLIC LICENSE
Project-URL: Homepage, https://github.com/software-students-fall2022/python-package-exercise-project-3-team-1
Project-URL: Repository, https://github.com/software-students-fall2022/python-package-exercise-project-3-team-1.git
Project-URL: Bug Tracker, https://github.com/software-students-fall2022/python-package-exercise-project-3-team-1/issues
Keywords: python,package,build,tutorial
Classifier: Programming Language :: Python :: 3
Classifier: Intended Audience :: Education
Classifier: License :: OSI Approved :: GNU General Public License v3 (GPLv3)
Classifier: Operating System :: OS Independent
Requires-Python: >=3.7
License-File: LICENSE
Provides-Extra: dev
Requires-Dist: pytest ; extra == 'dev'
